{"ranges":[{"road":"力行巷","zip6":"522012","even":0,"lane":0,"lane1":0,"alley":0,"alley1":0,"numStart":0,"numStart1":0,"numEnd":0,"numEnd1":0,"floorStart":0,"floorEnd":0},{"road":"三溪路1段","zip6":"522034","even":0,"lane":0,"lane1":0,"alley":0,"alley1":0,"numStart":0,"numStart1":0,"numEnd":0,"numEnd1":0,"floorStart":0,"floorEnd":0},{"road":"三溪路2段","zip6":"522034","even":0,"lane":0,"lane1":0,"alley":0,"alley1":0,"numStart":0,"numStart1":0,"numEnd":0,"numEnd1":0,"floorStart":0,"floorEnd":0},{"road":"三豐路","zip6":"522013","even":0,"lane":0,"lane1":0,"alley":0,"alley1":0,"numStart":1,"numStart1":0,"numEnd":289,"numEnd1":0,"floorStart":0,"floorEnd":0},{"road":"三豐路","zip6":"522011","even":0,"lane":0,"lane1":0,"alley":0,"alley1":0,"numStart":300,"numStart1":0,"numEnd":9999,"numEnd1":0,"floorStart":0,"floorEnd":0},{"road":"中山路1段","zip6":"522014","even":0,"lane":0,"lane1":0,"alley":0,"alley1":0,"numStart":0,"numStart1":0,"numEnd":0,"numEnd1":0,"floorStart":0,"floorEnd":0},{"road":"中山路2段","zip6":"522014","even":0,"lane":0,"lane1":0,"alley":0,"alley1":0,"numStart":0,"numStart1":0,"numEnd":0,"numEnd1":0,"floorStart":0,"floorEnd":0},{"road":"中正路1段","zip6":"522034","even":0,"lane":0,"lane1":0,"alley":0,"alley1":0,"numStart":0,"numStart1":0,"numEnd":0,"numEnd1":0,"floorStart":0,"floorEnd":0},{"road":"中正路2段","zip6":"522034","even":0,"lane":0,"lane1":0,"alley":0,"alley1":0,"numStart":0,"numStart1":0,"numEnd":0,"numEnd1":0,"floorStart":0,"floorEnd":0},{"road":"中正路3段","zip6":"522011","even":0,"lane":0,"lane1":0,"alley":0,"alley1":0,"numStart":0,"numStart1":0,"numEnd":0,"numEnd1":0,"floorStart":0,"floorEnd":0},{"road":"中庄巷","zip6":"522034","even":0,"lane":0,"lane1":0,"alley":0,"alley1":0,"numStart":1,"numStart1":0,"numEnd":188,"numEnd1":0,"floorStart":0,"floorEnd":0},{"road":"中庄巷","zip6":"522011","even":0,"lane":0,"lane1":0,"alley":0,"alley1":0,"numStart":190,"numStart1":0,"numEnd":9999,"numEnd1":0,"floorStart":0,"floorEnd":0},{"road":"中學路1段","zip6":"522014","even":0,"lane":0,"lane1":0,"alley":0,"alley1":0,"numStart":0,"numStart1":0,"numEnd":0,"numEnd1":0,"floorStart":0,"floorEnd":0},{"road":"中學路2段","zip6":"522014","even":0,"lane":0,"lane1":0,"alley":0,"alley1":0,"numStart":0,"numStart1":0,"numEnd":0,"numEnd1":0,"floorStart":0,"floorEnd":0},{"road":"中興路","zip6":"522014","even":0,"lane":0,"lane1":0,"alley":0,"alley1":0,"numStart":0,"numStart1":0,"numEnd":0,"numEnd1":0,"floorStart":0,"floorEnd":0},{"road":"仁興巷","zip6":"522015","even":0,"lane":0,"lane1":0,"alley":0,"alley1":0,"numStart":0,"numStart1":0,"numEnd":0,"numEnd1":0,"floorStart":0,"floorEnd":0},{"road":"仁豐路","zip6":"522034","even":0,"lane":0,"lane1":0,"alley":0,"alley1":0,"numStart":0,"numStart1":0,"numEnd":0,"numEnd1":0,"floorStart":0,"floorEnd":0},{"road":"公所路","zip6":"522013","even":0,"lane":0,"lane1":0,"alley":0,"alley1":0,"numStart":0,"numStart1":0,"numEnd":0,"numEnd1":0,"floorStart":0,"floorEnd":0},{"road":"公園五街","zip6":"522013","even":0,"lane":0,"lane1":0,"alley":0,"alley1":0,"numStart":0,"numStart1":0,"numEnd":0,"numEnd1":0,"floorStart":0,"floorEnd":0},{"road":"公園東路","zip6":"522014","even":0,"lane":0,"lane1":0,"alley":0,"alley1":0,"numStart":0,"numStart1":0,"numEnd":0,"numEnd1":0,"floorStart":0,"floorEnd":0},{"road":"公園路1段","zip6":"522012","even":0,"lane":0,"lane1":0,"alley":0,"alley1":0,"numStart":0,"numStart1":0,"numEnd":0,"numEnd1":0,"floorStart":0,"floorEnd":0},{"road":"公園路2段","zip6":"522012","even":0,"lane":0,"lane1":0,"alley":0,"alley1":0,"numStart":0,"numStart1":0,"numEnd":0,"numEnd1":0,"floorStart":0,"floorEnd":0},{"road":"斗中路","zip6":"522012","even":0,"lane":0,"lane1":0,"alley":0,"alley1":0,"numStart":0,"numStart1":0,"numEnd":0,"numEnd1":0,"floorStart":0,"floorEnd":0},{"road":"四維巷","zip6":"522014","even":0,"lane":0,"lane1":0,"alley":0,"alley1":0,"numStart":0,"numStart1":0,"numEnd":0,"numEnd1":0,"floorStart":0,"floorEnd":0},{"road":"平生巷","zip6":"522015","even":0,"lane":0,"lane1":0,"alley":0,"alley1":0,"numStart":1,"numStart1":0,"numEnd":160,"numEnd1":0,"floorStart":0,"floorEnd":0},{"road":"平生巷","zip6":"522014","even":0,"lane":0,"lane1":0,"alley":0,"alley1":0,"numStart":161,"numStart1":0,"numEnd":9999,"numEnd1":0,"floorStart":0,"floorEnd":0},{"road":"平和路1段","zip6":"522015","even":0,"lane":0,"lane1":0,"alley":0,"alley1":0,"numStart":0,"numStart1":0,"numEnd":0,"numEnd1":0,"floorStart":0,"floorEnd":0},{"road":"平和路2段","zip6":"522015","even":0,"lane":0,"lane1":0,"alley":0,"alley1":0,"numStart":0,"numStart1":0,"numEnd":0,"numEnd1":0,"floorStart":0,"floorEnd":0},{"road":"正田路","zip6":"522013","even":0,"lane":0,"lane1":0,"alley":0,"alley1":0,"numStart":0,"numStart1":0,"numEnd":0,"numEnd1":0,"floorStart":0,"floorEnd":0},{"road":"民生路1段","zip6":"522011","even":0,"lane":0,"lane1":0,"alley":0,"alley1":0,"numStart":0,"numStart1":0,"numEnd":0,"numEnd1":0,"floorStart":0,"floorEnd":0},{"road":"民生路2段","zip6":"522011","even":0,"lane":0,"lane1":0,"alley":0,"alley1":0,"numStart":0,"numStart1":0,"numEnd":0,"numEnd1":0,"floorStart":0,"floorEnd":0},{"road":"民生路3段","zip6":"522011","even":0,"lane":0,"lane1":0,"alley":0,"alley1":0,"numStart":0,"numStart1":0,"numEnd":0,"numEnd1":0,"floorStart":0,"floorEnd":0},{"road":"民和巷","zip6":"522034","even":0,"lane":0,"lane1":0,"alley":0,"alley1":0,"numStart":0,"numStart1":0,"numEnd":0,"numEnd1":0,"floorStart":0,"floorEnd":0},{"road":"民族路1段","zip6":"522013","even":0,"lane":0,"lane1":0,"alley":0,"alley1":0,"numStart":0,"numStart1":0,"numEnd":0,"numEnd1":0,"floorStart":0,"floorEnd":0},{"road":"民族路2段","zip6":"522013","even":0,"lane":0,"lane1":0,"alley":0,"alley1":0,"numStart":0,"numStart1":0,"numEnd":0,"numEnd1":0,"floorStart":0,"floorEnd":0},{"road":"民權路","zip6":"522015","even":0,"lane":0,"lane1":0,"alley":0,"alley1":0,"numStart":1,"numStart1":0,"numEnd":310,"numEnd1":0,"floorStart":0,"floorEnd":0},{"road":"民權路","zip6":"522014","even":0,"lane":0,"lane1":0,"alley":0,"alley1":0,"numStart":311,"numStart1":0,"numEnd":9999,"numEnd1":0,"floorStart":0,"floorEnd":0},{"road":"永福路2段","zip6":"522011","even":0,"lane":0,"lane1":0,"alley":0,"alley1":0,"numStart":0,"numStart1":0,"numEnd":0,"numEnd1":0,"floorStart":0,"floorEnd":0},{"road":"田仁路","zip6":"522011","even":0,"lane":0,"lane1":0,"alley":0,"alley1":0,"numStart":0,"numStart1":0,"numEnd":0,"numEnd1":0,"floorStart":0,"floorEnd":0},{"road":"田芳路","zip6":"522013","even":0,"lane":0,"lane1":0,"alley":0,"alley1":0,"numStart":0,"numStart1":0,"numEnd":0,"numEnd1":0,"floorStart":0,"floorEnd":0},{"road":"田美路","zip6":"522013","even":0,"lane":0,"lane1":0,"alley":0,"alley1":0,"numStart":0,"numStart1":0,"numEnd":0,"numEnd1":0,"floorStart":0,"floorEnd":0},{"road":"田溪路","zip6":"522034","even":0,"lane":0,"lane1":0,"alley":0,"alley1":0,"numStart":0,"numStart1":0,"numEnd":0,"numEnd1":0,"floorStart":0,"floorEnd":0},{"road":"田義路","zip6":"522011","even":0,"lane":0,"lane1":0,"alley":0,"alley1":0,"numStart":0,"numStart1":0,"numEnd":0,"numEnd1":0,"floorStart":0,"floorEnd":0},{"road":"光明巷","zip6":"522034","even":0,"lane":0,"lane1":0,"alley":0,"alley1":0,"numStart":0,"numStart1":0,"numEnd":0,"numEnd1":0,"floorStart":0,"floorEnd":0},{"road":"光復路1段","zip6":"522015","even":0,"lane":0,"lane1":0,"alley":0,"alley1":0,"numStart":0,"numStart1":0,"numEnd":0,"numEnd1":0,"floorStart":0,"floorEnd":0},{"road":"光復路2段","zip6":"522012","even":0,"lane":0,"lane1":0,"alley":0,"alley1":0,"numStart":0,"numStart1":0,"numEnd":0,"numEnd1":0,"floorStart":0,"floorEnd":0},{"road":"光復路3段","zip6":"522013","even":0,"lane":0,"lane1":0,"alley":0,"alley1":0,"numStart":205,"numStart1":0,"numEnd":9999,"numEnd1":0,"floorStart":0,"floorEnd":0},{"road":"光復路3段","zip6":"522053","even":0,"lane":0,"lane1":204,"alley":0,"alley1":0,"numStart":10,"numStart1":0,"numEnd":0,"numEnd1":0,"floorStart":0,"floorEnd":0},{"road":"光復路4段","zip6":"522034","even":0,"lane":0,"lane1":0,"alley":0,"alley1":0,"numStart":0,"numStart1":0,"numEnd":0,"numEnd1":0,"floorStart":0,"floorEnd":0},{"road":"光華巷","zip6":"522011","even":0,"lane":0,"lane1":0,"alley":0,"alley1":0,"numStart":0,"numStart1":0,"numEnd":0,"numEnd1":0,"floorStart":0,"floorEnd":0},{"road":"光榮巷","zip6":"522011","even":0,"lane":0,"lane1":0,"alley":0,"alley1":0,"numStart":0,"numStart1":0,"numEnd":0,"numEnd1":0,"floorStart":0,"floorEnd":0},{"road":"吉田路","zip6":"522013","even":0,"lane":0,"lane1":0,"alley":0,"alley1":0,"numStart":0,"numStart1":0,"numEnd":0,"numEnd1":0,"floorStart":0,"floorEnd":0},{"road":"吉安路","zip6":"522011","even":0,"lane":0,"lane1":0,"alley":0,"alley1":0,"numStart":0,"numStart1":0,"numEnd":0,"numEnd1":0,"floorStart":0,"floorEnd":0},{"road":"地政路","zip6":"522012","even":0,"lane":0,"lane1":0,"alley":0,"alley1":0,"numStart":0,"numStart1":0,"numEnd":0,"numEnd1":0,"floorStart":0,"floorEnd":0},{"road":"庄頭巷","zip6":"522013","even":0,"lane":0,"lane1":0,"alley":0,"alley1":0,"numStart":0,"numStart1":0,"numEnd":0,"numEnd1":0,"floorStart":0,"floorEnd":0},{"road":"和平巷","zip6":"522011","even":0,"lane":0,"lane1":0,"alley":0,"alley1":0,"numStart":0,"numStart1":0,"numEnd":0,"numEnd1":0,"floorStart":0,"floorEnd":0},{"road":"延平路","zip6":"522012","even":0,"lane":0,"lane1":0,"alley":0,"alley1":0,"numStart":0,"numStart1":0,"numEnd":0,"numEnd1":0,"floorStart":0,"floorEnd":0},{"road":"東平巷","zip6":"522014","even":0,"lane":0,"lane1":0,"alley":0,"alley1":0,"numStart":0,"numStart1":0,"numEnd":0,"numEnd1":0,"floorStart":0,"floorEnd":0},{"road":"前庄巷","zip6":"522034","even":0,"lane":0,"lane1":0,"alley":0,"alley1":0,"numStart":0,"numStart1":0,"numEnd":0,"numEnd1":0,"floorStart":0,"floorEnd":0},{"road":"建平路1段","zip6":"522012","even":0,"lane":0,"lane1":0,"alley":0,"alley1":0,"numStart":0,"numStart1":0,"numEnd":0,"numEnd1":0,"floorStart":0,"floorEnd":0},{"road":"建平路2段","zip6":"522012","even":0,"lane":0,"lane1":0,"alley":0,"alley1":0,"numStart":0,"numStart1":0,"numEnd":0,"numEnd1":0,"floorStart":0,"floorEnd":0},{"road":"後庄巷","zip6":"522034","even":0,"lane":0,"lane1":0,"alley":0,"alley1":0,"numStart":0,"numStart1":0,"numEnd":0,"numEnd1":0,"floorStart":0,"floorEnd":0},{"road":"柳鳳路","zip6":"522011","even":0,"lane":0,"lane1":0,"alley":0,"alley1":0,"numStart":0,"numStart1":0,"numEnd":0,"numEnd1":0,"floorStart":0,"floorEnd":0},{"road":"埔頭路","zip6":"522012","even":0,"lane":0,"lane1":0,"alley":0,"alley1":0,"numStart":0,"numStart1":0,"numEnd":0,"numEnd1":0,"floorStart":0,"floorEnd":0},{"road":"振華路","zip6":"522013","even":0,"lane":0,"lane1":0,"alley":0,"alley1":0,"numStart":0,"numStart1":0,"numEnd":0,"numEnd1":0,"floorStart":0,"floorEnd":0},{"road":"高東路","zip6":"522034","even":0,"lane":0,"lane1":0,"alley":0,"alley1":0,"numStart":0,"numStart1":0,"numEnd":0,"numEnd1":0,"floorStart":0,"floorEnd":0},{"road":"張厝巷","zip6":"522053","even":0,"lane":0,"lane1":0,"alley":0,"alley1":0,"numStart":0,"numStart1":0,"numEnd":0,"numEnd1":0,"floorStart":0,"floorEnd":0},{"road":"陸豐路","zip6":"522011","even":0,"lane":0,"lane1":0,"alley":0,"alley1":0,"numStart":0,"numStart1":0,"numEnd":0,"numEnd1":0,"floorStart":0,"floorEnd":0},{"road":"富農路1段","zip6":"522012","even":0,"lane":0,"lane1":0,"alley":0,"alley1":0,"numStart":0,"numStart1":0,"numEnd":0,"numEnd1":0,"floorStart":0,"floorEnd":0},{"road":"富農路2段","zip6":"522012","even":0,"lane":0,"lane1":0,"alley":0,"alley1":0,"numStart":0,"numStart1":0,"numEnd":0,"numEnd1":0,"floorStart":0,"floorEnd":0},{"road":"富農路3段","zip6":"522013","even":0,"lane":0,"lane1":0,"alley":0,"alley1":0,"numStart":0,"numStart1":0,"numEnd":0,"numEnd1":0,"floorStart":0,"floorEnd":0},{"road":"順圳巷","zip6":"522014","even":0,"lane":0,"lane1":0,"alley":0,"alley1":0,"numStart":0,"numStart1":0,"numEnd":0,"numEnd1":0,"floorStart":0,"floorEnd":0},{"road":"順安路","zip6":"522013","even":0,"lane":0,"lane1":0,"alley":0,"alley1":0,"numStart":0,"numStart1":0,"numEnd":0,"numEnd1":0,"floorStart":0,"floorEnd":0},{"road":"塗墩巷","zip6":"522034","even":0,"lane":0,"lane1":0,"alley":0,"alley1":0,"numStart":0,"numStart1":0,"numEnd":0,"numEnd1":0,"floorStart":0,"floorEnd":0},{"road":"新仁路","zip6":"522034","even":0,"lane":0,"lane1":0,"alley":0,"alley1":0,"numStart":0,"numStart1":0,"numEnd":0,"numEnd1":0,"floorStart":0,"floorEnd":0},{"road":"新民路","zip6":"522015","even":0,"lane":0,"lane1":0,"alley":0,"alley1":0,"numStart":1,"numStart1":0,"numEnd":160,"numEnd1":0,"floorStart":0,"floorEnd":0},{"road":"新民路","zip6":"522014","even":0,"lane":0,"lane1":0,"alley":0,"alley1":0,"numStart":161,"numStart1":0,"numEnd":9999,"numEnd1":0,"floorStart":0,"floorEnd":0},{"road":"新生路","zip6":"522011","even":0,"lane":0,"lane1":0,"alley":0,"alley1":0,"numStart":0,"numStart1":0,"numEnd":0,"numEnd1":0,"floorStart":0,"floorEnd":0},{"road":"新興路","zip6":"522015","even":0,"lane":0,"lane1":0,"alley":0,"alley1":0,"numStart":0,"numStart1":0,"numEnd":0,"numEnd1":0,"floorStart":0,"floorEnd":0},{"road":"溪畔巷","zip6":"522053","even":0,"lane":0,"lane1":0,"alley":0,"alley1":0,"numStart":0,"numStart1":0,"numEnd":0,"numEnd1":0,"floorStart":0,"floorEnd":0},{"road":"溪頂路","zip6":"522034","even":0,"lane":0,"lane1":0,"alley":0,"alley1":0,"numStart":0,"numStart1":0,"numEnd":0,"numEnd1":0,"floorStart":0,"floorEnd":0},{"road":"睦宜路","zip6":"522012","even":0,"lane":0,"lane1":0,"alley":0,"alley1":0,"numStart":0,"numStart1":0,"numEnd":0,"numEnd1":0,"floorStart":0,"floorEnd":0},{"road":"聖德巷","zip6":"522012","even":0,"lane":0,"lane1":0,"alley":0,"alley1":0,"numStart":0,"numStart1":0,"numEnd":0,"numEnd1":0,"floorStart":0,"floorEnd":0},{"road":"裕民路","zip6":"522012","even":0,"lane":0,"lane1":0,"alley":0,"alley1":0,"numStart":0,"numStart1":0,"numEnd":0,"numEnd1":0,"floorStart":0,"floorEnd":0},{"road":"裕豐路","zip6":"522034","even":0,"lane":0,"lane1":0,"alley":0,"alley1":0,"numStart":0,"numStart1":0,"numEnd":0,"numEnd1":0,"floorStart":0,"floorEnd":0},{"road":"漢光巷","zip6":"522011","even":0,"lane":0,"lane1":0,"alley":0,"alley1":0,"numStart":0,"numStart1":0,"numEnd":0,"numEnd1":0,"floorStart":0,"floorEnd":0},{"road":"福生巷","zip6":"522012","even":0,"lane":0,"lane1":0,"alley":0,"alley1":0,"numStart":0,"numStart1":0,"numEnd":0,"numEnd1":0,"floorStart":0,"floorEnd":0},{"road":"福新路","zip6":"522034","even":0,"lane":0,"lane1":0,"alley":0,"alley1":0,"numStart":0,"numStart1":0,"numEnd":0,"numEnd1":0,"floorStart":0,"floorEnd":0},{"road":"福德巷","zip6":"522014","even":0,"lane":0,"lane1":0,"alley":0,"alley1":0,"numStart":0,"numStart1":0,"numEnd":0,"numEnd1":0,"floorStart":0,"floorEnd":0},{"road":"鳳田路","zip6":"522011","even":0,"lane":0,"lane1":0,"alley":0,"alley1":0,"numStart":0,"numStart1":0,"numEnd":0,"numEnd1":0,"floorStart":0,"floorEnd":0},{"road":"慶豐路","zip6":"522011","even":0,"lane":0,"lane1":0,"alley":0,"alley1":0,"numStart":0,"numStart1":0,"numEnd":0,"numEnd1":0,"floorStart":0,"floorEnd":0},{"road":"模範巷","zip6":"522053","even":0,"lane":0,"lane1":0,"alley":0,"alley1":0,"numStart":0,"numStart1":0,"numEnd":0,"numEnd1":0,"floorStart":0,"floorEnd":0},{"road":"興農巷","zip6":"522012","even":0,"lane":0,"lane1":0,"alley":0,"alley1":0,"numStart":0,"numStart1":0,"numEnd":0,"numEnd1":0,"floorStart":0,"floorEnd":0},{"road":"豐田路","zip6":"522034","even":0,"lane":0,"lane1":0,"alley":0,"alley1":0,"numStart":0,"numStart1":0,"numEnd":0,"numEnd1":0,"floorStart":0,"floorEnd":0}]}